simple_repository/__init__.py
simple_repository/_types.py
simple_repository/abctract.py
simple_repository/exceptions.py
simple_repository/factory.py
simple_repository/implementation.py
simple_repository/protocols.py
simple_repository/utils.py
simple_repo_asyncsqla-2.1.0.dist-info/METADATA
simple_repo_asyncsqla-2.1.0.dist-info/WHEEL
simple_repo_asyncsqla-2.1.0.dist-info/licenses/License
simple_repo_asyncsqla-2.1.0.dist-info/RECORD
