Metadata-Version: 2.4
Name: simple-repo-asyncsqla
Version: 2.1.0
Summary: A lightweight and type-safe repository pattern implementation for SQLAlchemy async with Pydantic integration
Project-URL: Homepage, https://github.com/DustGalaxy/simple-repo-asyncsqla
Project-URL: Repository, https://github.com/DustGalaxy/simple-repo-asyncsqla
Project-URL: Issues, https://github.com/DustGalaxy/simple-repo-asyncsqla/issues
Author-email: DustGalaxy <103292379+DustGalaxy@users.noreply.github.com>
License-Expression: MIT
License-File: License
Keywords: async,crud,database,pydantic,repository-pattern,sqlalchemy
Classifier: Development Status :: 4 - Beta
Classifier: Intended Audience :: Developers
Classifier: License :: OSI Approved :: MIT License
Classifier: Operating System :: OS Independent
Classifier: Programming Language :: Python :: 3
Classifier: Programming Language :: Python :: 3.10
Classifier: Programming Language :: Python :: 3.11
Classifier: Programming Language :: Python :: 3.12
Classifier: Programming Language :: Python :: 3.13
Classifier: Topic :: Database
Classifier: Topic :: Software Development :: Libraries :: Python Modules
Classifier: Typing :: Typed
Requires-Python: >=3.10
Requires-Dist: sqlalchemy[asyncio]>=2.0.41
